[
  {
    "original_file": "Clavicular Crying.mp4",
    "gdrive_url": "https://drive.google.com/file/d/1wnv9RTsN8QZrMQFQrCfQcXVM9ZdDR6zT/view?usp=drivesdk",
    "new_title": "Crying_Over_Cheese_Profit_📈_#viralitypoly_#polymarket_#betting_#clips.mp4",
    "target_resolution": "1080:1920",
    "frame_filter": "scale=1080:1920:force_original_aspect_ratio=increase,crop=1080:1920",
    "caption_y_pos": "h-450",
    "font_color": "black",
    "bg_color": "white",
    "segments": [
      {
        "start": "00:00:29.720",
        "end": "00:00:33.280",
        "label": "THE_HOOK_CHEESE"
      },
      {
        "start": "00:00:10.000",
        "end": "00:00:17.380",
        "label": "THE_CRAZY_STAT"
      },
      {
        "start": "00:00:43.740",
        "end": "00:00:52.820",
        "label": "THE_BETTING_PLAN"
      },
      {
        "start": "00:00:53.560",
        "end": "00:00:55.260",
        "label": "FINAL_PAYOFF"
      }
    ]
  }
]
